fdf/__init__.py
fdf/cli.py
fdf/fdf.py
fdf-0.1.9.dist-info/AUTHORS.rst
fdf-0.1.9.dist-info/LICENSE
fdf-0.1.9.dist-info/METADATA
fdf-0.1.9.dist-info/WHEEL
fdf-0.1.9.dist-info/entry_points.txt
fdf-0.1.9.dist-info/top_level.txt
fdf-0.1.9.dist-info/RECORD
