Metadata-Version: 1.2
Name: fdf
Version: 0.1.9
Summary: File-system based Data Frame: manipulate self-explanatory dataset without writing codes.
Home-page: https://github.com/Ledenel/fdf
Author: Ledenel Intelli
Author-email: ledenelintelli@gmail.com
License: MIT license
Keywords: fdf
Platform: UNKNOWN
Classifier: Development Status :: 2 - Pre-Alpha
Classifier: Intended Audience :: Developers
Classifier: License :: OSI Approved :: MIT License
Classifier: Natural Language :: English
Classifier: Programming Language :: Python :: 3
Classifier: Programming Language :: Python :: 3.5
Classifier: Programming Language :: Python :: 3.6
Classifier: Programming Language :: Python :: 3.7
Classifier: Programming Language :: Python :: 3.8
Requires-Python: >=3.5
